securerun_manifest-0.1.0.dist-info/licenses/LICENSE
sr_ms/__init__.py
sr_ms/srms.py
securerun_manifest-0.1.0.dist-info/METADATA
securerun_manifest-0.1.0.dist-info/WHEEL
securerun_manifest-0.1.0.dist-info/entry_points.txt
securerun_manifest-0.1.0.dist-info/top_level.txt
securerun_manifest-0.1.0.dist-info/RECORD
