Metadata-Version: 2.4
Name: securerun-manifest
Version: 0.1.0
Summary: Secure Run Manifest (`sr-ms`) is a lightweight Python tool to securely lock, manage, and run Python scripts.
Author: Viren
License: License & Disclaimer
Requires-Python: >=3.9
License-File: LICENSE
Dynamic: license-file
